AUTHORS.rst
CONTRIBUTING.rst
HISTORY.rst
LICENSE
MANIFEST.in
README.rst
setup.cfg
setup.py
docs/Makefile
docs/authors.rst
docs/conf.py
docs/contributing.rst
docs/history.rst
docs/index.rst
docs/installation.rst
docs/make.bat
docs/readme.rst
docs/usage.rst
pypostman/__init__.py
pypostman/pypostman.py
pypostman.egg-info/PKG-INFO
pypostman.egg-info/SOURCES.txt
pypostman.egg-info/dependency_links.txt
pypostman.egg-info/not-zip-safe
pypostman.egg-info/top_level.txt
tests/__init__.py
tests/test_pypostman.py