Metadata-Version: 1.1
Name: pypostman
Version: 0.1.0
Summary: Simple Service that receives a Json structure with mail data, and sends an email to a preconfigured address
Home-page: https://github.com/skalanux/pypostman
Author: Juan Manuel Schillaci
Author-email: juan.schillaci@devecoop.com
License: BSD
Keywords: pypostman
Platform: UNKNOWN
Classifier: Development Status :: 2 - Pre-Alpha
Classifier: Intended Audience :: Developers
Classifier: License :: OSI Approved :: BSD License
Classifier: Natural Language :: English
Classifier: Programming Language :: Python :: 2
Classifier: Programming Language :: Python :: 2.6
Classifier: Programming Language :: Python :: 2.7
Classifier: Programming Language :: Python :: 3
Classifier: Programming Language :: Python :: 3.3
Classifier: Programming Language :: Python :: 3.4
